{
  "id": "3100Series",
  "series": "3100 系列",
  "title": "可程式低歐姆計",
  "subtitle": "精密電阻測量範圍從 0.001mΩ 至 1.9999MΩ",
  "image": "/images/products/transparent/3100.png",
  "overview": {
    "paragraphs": [
      "WK 3100 是一款可程式低歐姆計，設計用於在從 0.001mΩ 至 1.9999MΩ 的寬範圍內提供精確的電阻測量。其先進功能和高速度能力使其非常適合用於自動化系統和各種測試環境，確保在最小溫度影響下進行準確的元件評估。"
    ]
  },
  "applications": [
    "需要精確電阻測量的電子製造和品質控制環境",
    "高速度和準確元件分析至關重要的測試環境",
    "需要多功能、可靠且準確的測試設備進行元件特性分析的實驗室和研發中心"
  ],
  "features": [
    {
      "title": "寬廣測量範圍",
      "description": "能夠測量從 0.001mΩ 至 1.9999MΩ 的電阻，確保在處理各種元件時的靈活性"
    },
    {
      "title": "高精度",
      "description": "提供 ±0.1% 讀數的優異精度水平，增強測試結果的可靠性"
    },
    {
      "title": "先進測量模式",
      "description": "提供電平模式和脈衝測量模式，脈衝模式可減少測試過程中的溫度影響"
    },
    {
      "title": "快速測試能力",
      "description": "配備高速快速類比數位轉換器 (FADC)，實現最高 14ms 的最大測試速度，加速測試過程"
    },
    {
      "title": "全面顯示和控制",
      "description": "配備 240 x 64 圖形 LCD 顯示器，提供清晰詳細的讀數，並可輕鬆瀏覽測試設定"
    },
    {
      "title": "多功能觸發和測試模式",
      "description": "支援內部和外部觸發，具有自動或手動量程和歸零校準功能，以提高精度"
    },
    {
      "title": "全面分選和比較功能",
      "description": "包括分選分選和 HI/LOW 限制比較器功能，促進元件分選和品質控制評估"
    },
    {
      "title": "連接選項",
      "description": "配備 RS232 和 HANDLER 組合介面，便於與其他系統整合"
    }
  ],
  "specifications": [
    {
      "heading": "測量範圍",
      "content": ["電平：0.001 mΩ ~ 1.9999MΩ", "脈衝：0.001 mΩ ~ 1.9999Ω"]
    },
    {
      "heading": "電平模式規格",
      "list": [
        "20 mΩ 量程：0.000 ~ 19.999，0.001mΩ 解析度，1A 直流電流，±(讀數的 0.1% + 5 位數) 精度",
        "200 mΩ 量程：0.00 ~ 199.99，0.01mΩ 解析度，100mA 直流電流，±(讀數的 0.1% + 5 位數) 精度",
        "2Ω 量程：0.0000 ~ 19.999，0.0001Ω 解析度，100mA 直流電流，±(讀數的 0.1% + 5 位數) 精度",
        "20 Ω 量程：0.000 ~ 19.999，0.001Ω 解析度，10mA 直流電流，±(讀數的 0.1% + 5 位數) 精度",
        "20 Ω 量程（高）：0.000 ~ 10.000，0.01Ω 解析度，1mA 直流電流，±(讀數的 0.1% + 5 位數) 精度",
        "2 kΩ 量程：0.0000 ~ 1.9999，0.0001kΩ 解析度，1mA 直流電流，±(讀數的 0.1% + 5 位數) 精度",
        "20 kΩ 量程：0.000 ~ 19.999，0.001kΩ 解析度，100µA 直流電流，±(讀數的 0.1% + 5 位數) 精度",
        "200 kΩ 量程：0.00 ~ 199.99，0.01kΩ 解析度，10µA 直流電流，±(讀數的 0.1% + 5 位數) 精度",
        "2 MΩ 量程：0.0000 ~ 1.9999，0.0001MΩ 解析度，1µA 直流電流，±(讀數的 0.1% + 5 位數) 精度"
      ]
    },
    {
      "heading": "脈衝模式規格",
      "list": [
        "20 mΩ 量程：0.000 ~ 19.999，0.001mΩ 解析度，±50mA 電流，±(讀數的 0.5% + 10 位數) 精度",
        "200 mΩ 量程：0.00 ~ 199.99，0.01mΩ 解析度，±50mA 電流，±(讀數的 0.5% + 10 位數) 精度",
        "2Ω 量程：0.0000 ~ 1.9999，0.0001Ω 解析度，±50mA 電流，±(讀數的 0.2% + 10 位數) 精度"
      ]
    },
    {
      "heading": "測試速度",
      "content": [
        "電平：慢速：135ms，快速：68ms，最大：14ms",
        "脈衝：慢速：310ms，快速：170ms，最大：140ms"
      ]
    },
    {
      "heading": "開路電壓",
      "content": ["20 mΩ ~ 20 Ω：<1.0V", "200 Ω ~ 2 MΩ：< 5.5V"]
    },
    {
      "heading": "溫度係數",
      "content": ["±(0.01% + 0.5 位數) / °C"]
    },
    {
      "heading": "測試模式",
      "content": ["四線測試"]
    },
    {
      "heading": "顯示 LCD",
      "content": ["240 × 64 圖形顯示，4 1/2 位數"]
    },
    {
      "heading": "觸發模式",
      "content": ["內部、外部"]
    },
    {
      "heading": "量程",
      "content": ["自動或手動"]
    },
    {
      "heading": "功能",
      "content": ["自動量程、歸零校準"]
    },
    {
      "heading": "介面",
      "content": ["RS232/HANDLER 組合介面"]
    },
    {
      "heading": "記憶體",
      "content": ["最多 100 組記憶體"]
    },
    {
      "heading": "電池備份",
      "content": ["測量狀態：測量範圍、比較器設定"]
    },
    {
      "heading": "比較器",
      "content": [
        "HI/LO：判斷比較器標準值設定、高低限制設定、通過/失敗判斷、警報指示",
        "分選分選：分選比較器參考值和 HI-LO 限制設定（按分選編號或步驟模式）、DCR 值限制、8 個分選用於分選和分選總計數"
      ]
    },
    {
      "heading": "配件",
      "content": ["測試夾、電源線、操作手冊、校準證書"]
    },
    {
      "heading": "電源",
      "content": ["115/230 V ±10%，50/60 Hz"]
    },
    {
      "heading": "尺寸",
      "content": ["270(寬) x 110(高) x 310(深) mm"]
    },
    {
      "heading": "重量",
      "content": ["4.5 kg"]
    }
  ],
  "datasheet": "/datasheets/instruments/WK3100.pdf"
}
